numbering/__init__.py
numbering/convert.py
numbering/enums.py
numbering/numbering.py
numbering-0.1.5.dist-info/LICENSE
numbering-0.1.5.dist-info/METADATA
numbering-0.1.5.dist-info/WHEEL
numbering-0.1.5.dist-info/top_level.txt
numbering-0.1.5.dist-info/RECORD
