Metadata-Version: 2.1
Name: numbering
Version: 0.1.5
Home-page: https://github.com/Madung2/Numbering
Author: Madung2
Author-email: tuliphan91@gmail.com
Classifier: Programming Language :: Python :: 3.12
Classifier: License :: OSI Approved :: MIT License
Classifier: Operating System :: OS Independent
Requires-Python: >=3.12
License-File: LICENSE
Requires-Dist: python-docx >=1.1.2
Requires-Dist: python-dotenv >=1.0.1
